libname/__init__.py
libname/mel.py
melmel-0.1.0.dist-info/METADATA
melmel-0.1.0.dist-info/WHEEL
melmel-0.1.0.dist-info/top_level.txt
melmel-0.1.0.dist-info/RECORD
