Metadata-Version: 2.1
Name: melmel
Version: 0.1.0
Summary: Simplifies and adds fun things to Python
Home-page: UNKNOWN
Author: Melonpod
Author-email: <melonnator32@gmail.com>
License: UNKNOWN
Keywords: python,simple,code,fun
Platform: UNKNOWN
Classifier: Development Status :: 3 - Alpha
Classifier: Intended Audience :: Developers
Classifier: Programming Language :: Python :: 3
Classifier: Operating System :: Unix
Classifier: Operating System :: MacOS :: MacOS X
Classifier: Operating System :: Microsoft :: Windows
Requires-Dist: random
Requires-Dist: math
Requires-Dist: os
Requires-Dist: datetime
Requires-Dist: colorama
